heartbeat/__init__.py
heartbeat/heartbeat.py
neuon_heartbeat-0.1.5.dist-info/METADATA
neuon_heartbeat-0.1.5.dist-info/WHEEL
neuon_heartbeat-0.1.5.dist-info/top_level.txt
neuon_heartbeat-0.1.5.dist-info/RECORD
