Metadata-Version: 2.1
Name: neuon-heartbeat
Version: 0.1.5
Summary: Generic Heartbeat module using MongoDB as record
Author: holmes
Author-email: tidusyuna88@gmail.com
Classifier: Programming Language :: Python :: 3
Classifier: License :: OSI Approved :: MIT License
Classifier: Operating System :: OS Independent
Requires-Python: >=3.6
Requires-Dist: pymongo >=4.7.3
Requires-Dist: neuon >=0.0.1
Requires-Dist: neuondb >=0.1.0
